Metadata-Version: 2.1
Name: raspiSensors
Version: 2019.3.26
Summary: A series of convenience functions for Raspbery PI sensors
Home-page: https://github.com/hanshof/raspiSensors
Author: Johann Hofstaetter
Author-email: hanshof@mailbox.org
Maintainer: Johann Hofstaetter
Maintainer-email: hanshof@mailbox.org
License: MIT
Download-URL: https://github.com/hanshof/raspiSensors/archive/2019.3.26.tar.gz
Keywords: Raspberry PI,Sensor,Robots
Platform: UNKNOWN
Classifier: Development Status :: 5 - Production/Stable
Classifier: Intended Audience :: Developers
Classifier: Topic :: Scientific/Engineering :: Interface Engine/Protocol Translator
Classifier: License :: OSI Approved :: GNU General Public License v3 (GPLv3)
Classifier: Programming Language :: Python :: 3
Classifier: Programming Language :: Python :: 3.5
